parcel_data_collector/__init__.py
parcel_data_collector/config.py
parcel_data_collector/county_property_data.py
parcel_data_collector/database_downloader.py
parcel_data_collector/logger.py
parcel_data_collector/helpers/__init__.py
parcel_data_collector/helpers/county_dataframe.py
parcel_data_collector/helpers/downloader.py
parcel_data_collector/helpers/gzipconverter.py
parcel_data_collector/helpers/misc.py
parcel_data_collector/helpers/unzipper.py
parcel_data_collector-0.1.2.dist-info/METADATA
parcel_data_collector-0.1.2.dist-info/WHEEL
parcel_data_collector-0.1.2.dist-info/top_level.txt
parcel_data_collector-0.1.2.dist-info/RECORD
