Metadata-Version: 2.1
Name: parcel-data-collector
Version: 0.1.2
Summary: A package for collecting and analyzing data
Home-page: https://github.com/pdiegel/Parcel-Data-Collector
Author: Philip Diegel
Author-email: philipdiegel@gmail.com
Classifier: Development Status :: 3 - Alpha
Classifier: Intended Audience :: Developers
Classifier: License :: OSI Approved :: MIT License
Classifier: Programming Language :: Python :: 3.11
Requires-Python: >=3.11
Requires-Dist: beautifulsoup4 (==4.12.0)
Requires-Dist: pandas (==1.5.2)
Requires-Dist: playwright (==1.31.1)
Requires-Dist: PyYAML (==6.0)
Requires-Dist: requests (==2.28.1)
